netsecgame/__init__.py
netsecgame/game_components.py
netsecgame/agents/__init__.py
netsecgame/agents/base_agent.py
netsecgame/game/__init__.py
netsecgame/game/agent_server.py
netsecgame/game/config_parser.py
netsecgame/game/configuration_manager.py
netsecgame/game/coordinator.py
netsecgame/game/global_defender.py
netsecgame/game/scenarios/__init__.py
netsecgame/game/scenarios/one_net.py
netsecgame/game/scenarios/scenario_configuration.py
netsecgame/game/scenarios/smaller_scenario_configuration.py
netsecgame/game/scenarios/test_scenario_configuration.py
netsecgame/game/scenarios/three_net_scenario.py
netsecgame/game/scenarios/tiny_scenario_configuration.py
netsecgame/game/scenarios/two_nets.py
netsecgame/game/scenarios/two_nets_small.py
netsecgame/game/scenarios/two_nets_tiny.py
netsecgame/game/worlds/NetSecGame.py
netsecgame/game/worlds/WhiteBoxNetSecGame.py
netsecgame/game/worlds/__init__.py
netsecgame/utils/aidojo_log_colorizer.py
netsecgame/utils/trajectory_recorder.py
netsecgame/utils/utils.py
netsecgame-0.1.0.dist-info/licenses/LICENSE
netsecgame-0.1.0.dist-info/METADATA
netsecgame-0.1.0.dist-info/WHEEL
netsecgame-0.1.0.dist-info/top_level.txt
netsecgame-0.1.0.dist-info/RECORD
