Metadata-Version: 2.4
Name: netsecgame
Version: 0.1.0
Summary: A package for coordinating AI-driven network simulation games.
Author-email: Ondrej Lukas <ondrej.lukas@aic.fel.cvut.cz>, Sebastian Garcia <sebastian.garcia@agents.fel.cvut.cz>, Maria Rigaki <maria.rigaki@aic.fel.cvut.cz>
License-Expression: GPL-3.0-or-later
Project-URL: Homepage, https://github.com/stratosphereips/NetSecGame
Project-URL: Repository, https://github.com/stratosphereips/NetSecGame
Project-URL: Documentation, https://github.com/stratosphereips/NetSecGame
Project-URL: Issues, https://github.com/stratosphereips/NetSecGame/issues
Classifier: Programming Language :: Python :: 3
Classifier: Topic :: Scientific/Engineering :: Artificial Intelligence
Requires-Python: >=3.12
License-File: LICENSE
Requires-Dist: jsonlines>=4.0.0
Requires-Dist: netaddr==0.9.0
Provides-Extra: server
Requires-Dist: aiohttp>=3.11; extra == "server"
Requires-Dist: cyst-core>=0.5.0; extra == "server"
Requires-Dist: Faker>=23.2; extra == "server"
Requires-Dist: numpy>=1.26; extra == "server"
Requires-Dist: PyYAML>=6.0; extra == "server"
Requires-Dist: requests>=2.32; extra == "server"
Provides-Extra: dev
Requires-Dist: netsecgame[server]; extra == "dev"
Requires-Dist: pytest; extra == "dev"
Requires-Dist: ruff; extra == "dev"
Requires-Dist: pytest-asyncio; extra == "dev"
Requires-Dist: twine; extra == "dev"
Provides-Extra: docs
Requires-Dist: mkdocs; extra == "docs"
Requires-Dist: mkdocs-material; extra == "docs"
Requires-Dist: mkdocstrings[python]; extra == "docs"
Requires-Dist: pymdown-extensions; extra == "docs"
Dynamic: license-file
